{
  "person_id": 11927,
  "name": "Mary White",
  "stage_name": null,
  "nodes": [
    {
      "id": "song:11923",
      "song_id": 11923,
      "title": "Hurry Up and Love",
      "genre": "Indie Folk",
      "notable": true,
      "release_year": 2023,
      "single": true,
      "own": true,
      "artist_id": 11927,
      "artist_name": "Mary White",
      "influence": 0,
      "influence_breakdown": {
        "cover": 0,
        "sample": 0,
        "reference": 0,
        "style": 0
      },
      "relation_types": []
    }
  ],
  "links": []
}