{
  "person_id": 13037,
  "name": "Janet Lewis",
  "stage_name": null,
  "nodes": [
    {
      "id": "song:13627",
      "song_id": 13627,
      "title": "Roots and Resonance",
      "genre": "Indie Rock",
      "notable": true,
      "release_year": 2010,
      "single": true,
      "own": true,
      "artist_id": 13037,
      "artist_name": "Janet Lewis",
      "influence": 0,
      "influence_breakdown": {
        "cover": 0,
        "sample": 0,
        "reference": 0,
        "style": 0
      },
      "relation_types": []
    },
    {
      "id": "song:13035",
      "song_id": 13035,
      "title": "Mirage of Midnight Sands",
      "genre": "Indie Rock",
      "notable": true,
      "release_year": 2010,
      "single": true,
      "own": true,
      "artist_id": 13037,
      "artist_name": "Janet Lewis",
      "influence": 7,
      "influence_breakdown": {
        "cover": 1,
        "sample": 0,
        "reference": 0,
        "style": 1
      },
      "relation_types": []
    },
    {
      "id": "song:6699",
      "song_id": 6699,
      "title": "Beside Me",
      "genre": "Indie Rock",
      "notable": true,
      "release_year": 2021,
      "single": true,
      "own": false,
      "artist_id": 6701,
      "artist_name": "Tiya Desai",
      "influence": 0,
      "influence_breakdown": {
        "cover": 0,
        "sample": 0,
        "reference": 0,
        "style": 0
      },
      "relation_types": [
        "CoverOf"
      ]
    }
  ],
  "links": [
    {
      "source": "song:13627",
      "target": "song:13035",
      "type": "InStyleOf"
    },
    {
      "source": "song:6699",
      "target": "song:13035",
      "type": "CoverOf"
    }
  ]
}