{
  "person_id": 1304,
  "name": "Rüdiger Graf",
  "stage_name": null,
  "nodes": [
    {
      "id": "song:2851",
      "work_type": "Song",
      "work_id": 2851,
      "title": "Glasses Raised",
      "genre": "Southern Gothic Rock",
      "notable": true,
      "release_year": 2027,
      "single": true,
      "own": true,
      "artist_id": 1304,
      "artist_name": "Rüdiger Graf",
      "influence": 0,
      "influence_breakdown": {
        "cover": 0,
        "sample": 0,
        "reference": 0,
        "style": 0
      },
      "relation_types": [],
      "collaborators": []
    },
    {
      "id": "song:5598",
      "work_type": "Song",
      "work_id": 5598,
      "title": "Whispers of an Unbound Horizon",
      "genre": "Oceanus Folk",
      "notable": false,
      "release_year": 2017,
      "single": false,
      "own": true,
      "artist_id": 1304,
      "artist_name": "Rüdiger Graf",
      "influence": 0,
      "influence_breakdown": {
        "cover": 0,
        "sample": 0,
        "reference": 0,
        "style": 0
      },
      "relation_types": [],
      "collaborators": [
        {
          "person_id": 3079,
          "name": "Yang Yao",
          "stage_name": null,
          "roles": [
            "LyricistOf"
          ],
          "predicted_score": 3.4515953
        },
        {
          "person_id": 3195,
          "name": "Lei Zeng",
          "stage_name": null,
          "roles": [
            "PerformerOf"
          ],
          "predicted_score": 2.458484
        }
      ]
    },
    {
      "id": "song:6054",
      "work_type": "Song",
      "work_id": 6054,
      "title": "Colorful Traditions",
      "genre": "Dream Pop",
      "notable": true,
      "release_year": 2026,
      "single": true,
      "own": true,
      "artist_id": 1304,
      "artist_name": "Rüdiger Graf",
      "influence": 5,
      "influence_breakdown": {
        "cover": 0,
        "sample": 0,
        "reference": 1,
        "style": 1
      },
      "relation_types": [],
      "collaborators": [
        {
          "person_id": 6055,
          "name": "Yong Fu",
          "stage_name": null,
          "roles": [
            "LyricistOf",
            "PerformerOf"
          ],
          "predicted_score": 3.4343328
        },
        {
          "person_id": 6056,
          "name": "Xiulan Qin",
          "stage_name": null,
          "roles": [
            "PerformerOf"
          ],
          "predicted_score": 3.4343328
        },
        {
          "person_id": 6060,
          "name": "Xiulan Yin",
          "stage_name": null,
          "roles": [
            "PerformerOf"
          ],
          "predicted_score": 3.0449867
        },
        {
          "person_id": 6057,
          "name": "Anthony Hancock",
          "stage_name": null,
          "roles": [
            "PerformerOf",
            "ProducerOf"
          ],
          "predicted_score": 3.0446894
        },
        {
          "person_id": 6058,
          "name": "Li Bai",
          "stage_name": null,
          "roles": [
            "PerformerOf",
            "ProducerOf"
          ],
          "predicted_score": 2.3986783
        },
        {
          "person_id": 6059,
          "name": "Brandon Kirby",
          "stage_name": null,
          "roles": [
            "PerformerOf"
          ],
          "predicted_score": 2.3986783
        }
      ]
    },
    {
      "id": "song:14279",
      "work_type": "Song",
      "work_id": 14279,
      "title": "Artificial Intuition Node",
      "genre": "Lo-Fi Electronica",
      "notable": true,
      "release_year": 2024,
      "single": true,
      "own": true,
      "artist_id": 1304,
      "artist_name": "Rüdiger Graf",
      "influence": 0,
      "influence_breakdown": {
        "cover": 0,
        "sample": 0,
        "reference": 0,
        "style": 0
      },
      "relation_types": [],
      "collaborators": [
        {
          "person_id": 14280,
          "name": "Chao Liao",
          "stage_name": null,
          "roles": [
            "PerformerOf"
          ],
          "predicted_score": 2.396829
        }
      ]
    },
    {
      "id": "song:15369",
      "work_type": "Song",
      "work_id": 15369,
      "title": "Cosmic Cartography",
      "genre": "Space Rock",
      "notable": true,
      "release_year": 2026,
      "single": true,
      "own": true,
      "artist_id": 1304,
      "artist_name": "Rüdiger Graf",
      "influence": 0,
      "influence_breakdown": {
        "cover": 0,
        "sample": 0,
        "reference": 0,
        "style": 0
      },
      "relation_types": [],
      "collaborators": [
        {
          "person_id": 12510,
          "name": "Min Yin",
          "stage_name": null,
          "roles": [
            "PerformerOf"
          ],
          "predicted_score": 3.4402542
        },
        {
          "person_id": 15224,
          "name": "Juan Shi",
          "stage_name": null,
          "roles": [
            "PerformerOf"
          ],
          "predicted_score": 3.4282305
        },
        {
          "person_id": 15225,
          "name": "Guiying Shi",
          "stage_name": null,
          "roles": [
            "PerformerOf"
          ],
          "predicted_score": 3.051812
        },
        {
          "person_id": 15370,
          "name": "Paige Mitchell",
          "stage_name": "DRIP$ETTA",
          "roles": [
            "LyricistOf"
          ],
          "predicted_score": 2.3988938
        },
        {
          "person_id": 15371,
          "name": "Yong Qiao",
          "stage_name": null,
          "roles": [
            "PerformerOf"
          ],
          "predicted_score": 2.3988938
        }
      ]
    },
    {
      "id": "song:1298",
      "work_type": "Song",
      "work_id": 1298,
      "title": "Concrete Kingdom",
      "genre": "Dream Pop",
      "notable": true,
      "release_year": 2026,
      "single": true,
      "own": true,
      "artist_id": 1304,
      "artist_name": "Rüdiger Graf",
      "influence": 0,
      "influence_breakdown": {
        "cover": 0,
        "sample": 0,
        "reference": 0,
        "style": 0
      },
      "relation_types": [],
      "collaborators": [
        {
          "person_id": 1302,
          "name": "Ming Xue",
          "stage_name": null,
          "roles": [
            "ComposerOf"
          ],
          "predicted_score": 3.436135
        },
        {
          "person_id": 1303,
          "name": "Min Duan",
          "stage_name": null,
          "roles": [
            "PerformerOf"
          ],
          "predicted_score": 3.4350893
        },
        {
          "person_id": 1299,
          "name": "Gang Ye",
          "stage_name": null,
          "roles": [
            "PerformerOf"
          ],
          "predicted_score": 2.3983319
        },
        {
          "person_id": 1301,
          "name": "Lei Han",
          "stage_name": null,
          "roles": [
            "LyricistOf"
          ],
          "predicted_score": 2.3983319
        },
        {
          "person_id": 1300,
          "name": "Xia Liang",
          "stage_name": null,
          "roles": [
            "ComposerOf"
          ],
          "predicted_score": 2.3977478
        }
      ]
    },
    {
      "id": "song:13516",
      "work_type": "Song",
      "work_id": 13516,
      "title": "Rings and Revelations",
      "genre": "Oceanus Folk",
      "notable": true,
      "release_year": 2024,
      "single": false,
      "own": true,
      "artist_id": 1304,
      "artist_name": "Rüdiger Graf",
      "influence": 6,
      "influence_breakdown": {
        "cover": 0,
        "sample": 1,
        "reference": 0,
        "style": 1
      },
      "relation_types": [],
      "collaborators": [
        {
          "person_id": 1085,
          "name": "Lupe Miró",
          "stage_name": null,
          "roles": [
            "LyricistOf"
          ],
          "predicted_score": 4.514692
        },
        {
          "person_id": 13517,
          "name": "Qiang Zhu",
          "stage_name": null,
          "roles": [
            "PerformerOf"
          ],
          "predicted_score": 3.046315
        },
        {
          "person_id": 13518,
          "name": "Paulo Oestrovsky",
          "stage_name": null,
          "roles": [
            "PerformerOf"
          ],
          "predicted_score": 3.0459218
        }
      ]
    },
    {
      "id": "song:15222",
      "work_type": "Song",
      "work_id": 15222,
      "title": "The Machinery of Dreams",
      "genre": "Jazz Surf Rock",
      "notable": true,
      "release_year": 2026,
      "single": false,
      "own": true,
      "artist_id": 1304,
      "artist_name": "Rüdiger Graf",
      "influence": 5,
      "influence_breakdown": {
        "cover": 1,
        "sample": 0,
        "reference": 0,
        "style": 0
      },
      "relation_types": [],
      "collaborators": [
        {
          "person_id": 12510,
          "name": "Min Yin",
          "stage_name": null,
          "roles": [
            "PerformerOf"
          ],
          "predicted_score": 3.4402542
        },
        {
          "person_id": 15224,
          "name": "Juan Shi",
          "stage_name": null,
          "roles": [
            "PerformerOf"
          ],
          "predicted_score": 3.4282305
        },
        {
          "person_id": 15225,
          "name": "Guiying Shi",
          "stage_name": null,
          "roles": [
            "PerformerOf"
          ],
          "predicted_score": 3.051812
        },
        {
          "person_id": 15223,
          "name": "Tao Xie",
          "stage_name": null,
          "roles": [
            "PerformerOf"
          ],
          "predicted_score": 2.3979979
        }
      ]
    },
    {
      "id": "song:16371",
      "work_type": "Song",
      "work_id": 16371,
      "title": "Painted Heavens",
      "genre": "Lo-Fi Electronica",
      "notable": true,
      "release_year": 2018,
      "single": false,
      "own": true,
      "artist_id": 1304,
      "artist_name": "Rüdiger Graf",
      "influence": 0,
      "influence_breakdown": {
        "cover": 0,
        "sample": 0,
        "reference": 0,
        "style": 0
      },
      "relation_types": [],
      "collaborators": [
        {
          "person_id": 172,
          "name": "Lei Liao",
          "stage_name": null,
          "roles": [
            "PerformerOf",
            "ProducerOf"
          ],
          "predicted_score": 4.343267
        },
        {
          "person_id": 5481,
          "name": "Min Zhao",
          "stage_name": null,
          "roles": [
            "PerformerOf"
          ],
          "predicted_score": 3.4297187
        }
      ]
    },
    {
      "id": "song:11467",
      "work_type": "Song",
      "work_id": 11467,
      "title": "Percussive Daydream",
      "genre": "Lo-Fi Electronica",
      "notable": true,
      "release_year": 2013,
      "single": true,
      "own": true,
      "artist_id": 1304,
      "artist_name": "Rüdiger Graf",
      "influence": 15,
      "influence_breakdown": {
        "cover": 1,
        "sample": 0,
        "reference": 2,
        "style": 2
      },
      "relation_types": [],
      "collaborators": [
        {
          "person_id": 172,
          "name": "Lei Liao",
          "stage_name": null,
          "roles": [
            "PerformerOf"
          ],
          "predicted_score": 4.343267
        }
      ]
    },
    {
      "id": "song:7089",
      "work_type": "Song",
      "work_id": 7089,
      "title": "Divine Restraint",
      "genre": "Dream Pop",
      "notable": true,
      "release_year": 2028,
      "single": false,
      "own": false,
      "artist_id": 3868,
      "artist_name": "Xiulan Lu",
      "influence": 0,
      "influence_breakdown": {
        "cover": 0,
        "sample": 0,
        "reference": 0,
        "style": 0
      },
      "relation_types": [
        "InStyleOf"
      ],
      "collaborators": [
        {
          "person_id": 6055,
          "name": "Yong Fu",
          "stage_name": null,
          "roles": [
            "PerformerOf"
          ],
          "predicted_score": 3.4343328
        },
        {
          "person_id": 6056,
          "name": "Xiulan Qin",
          "stage_name": null,
          "roles": [
            "ComposerOf"
          ],
          "predicted_score": 3.4343328
        },
        {
          "person_id": 3868,
          "name": "Xiulan Lu",
          "stage_name": null,
          "roles": [
            "PerformerOf"
          ],
          "predicted_score": 3.407993
        },
        {
          "person_id": 6057,
          "name": "Anthony Hancock",
          "stage_name": null,
          "roles": [
            "PerformerOf",
            "ProducerOf"
          ],
          "predicted_score": 3.0446894
        },
        {
          "person_id": 7090,
          "name": "Yan Yang",
          "stage_name": null,
          "roles": [
            "ComposerOf",
            "PerformerOf"
          ],
          "predicted_score": 2.4004812
        },
        {
          "person_id": 7091,
          "name": "Jie Zhang",
          "stage_name": null,
          "roles": [
            "PerformerOf"
          ],
          "predicted_score": 2.4004812
        }
      ]
    },
    {
      "id": "song:13158",
      "work_type": "Song",
      "work_id": 13158,
      "title": "Whispers of the Parish Boundary",
      "genre": "Dream Pop",
      "notable": true,
      "release_year": 2028,
      "single": true,
      "own": false,
      "artist_id": 3868,
      "artist_name": "Xiulan Lu",
      "influence": 0,
      "influence_breakdown": {
        "cover": 0,
        "sample": 0,
        "reference": 0,
        "style": 0
      },
      "relation_types": [
        "InterpolatesFrom"
      ],
      "collaborators": [
        {
          "person_id": 6055,
          "name": "Yong Fu",
          "stage_name": null,
          "roles": [
            "PerformerOf"
          ],
          "predicted_score": 3.4343328
        },
        {
          "person_id": 6056,
          "name": "Xiulan Qin",
          "stage_name": null,
          "roles": [
            "ComposerOf",
            "PerformerOf"
          ],
          "predicted_score": 3.4343328
        },
        {
          "person_id": 3868,
          "name": "Xiulan Lu",
          "stage_name": null,
          "roles": [
            "LyricistOf",
            "PerformerOf"
          ],
          "predicted_score": 3.407993
        },
        {
          "person_id": 6060,
          "name": "Xiulan Yin",
          "stage_name": null,
          "roles": [
            "PerformerOf",
            "ProducerOf"
          ],
          "predicted_score": 3.0449867
        },
        {
          "person_id": 13159,
          "name": "Ming Pan",
          "stage_name": null,
          "roles": [
            "PerformerOf"
          ],
          "predicted_score": 2.4005203
        },
        {
          "person_id": 13160,
          "name": "Fang Wan",
          "stage_name": null,
          "roles": [
            "PerformerOf"
          ],
          "predicted_score": 2.4005203
        }
      ]
    },
    {
      "id": "album:7147",
      "work_type": "Album",
      "work_id": 7147,
      "title": "Distant Horizons",
      "genre": "Oceanus Folk",
      "notable": false,
      "release_year": 2029,
      "single": false,
      "own": false,
      "artist_id": 7148,
      "artist_name": "Gang Xiong",
      "influence": 0,
      "influence_breakdown": {
        "cover": 0,
        "sample": 0,
        "reference": 0,
        "style": 0
      },
      "relation_types": [
        "InStyleOf"
      ],
      "collaborators": [
        {
          "person_id": 7148,
          "name": "Gang Xiong",
          "stage_name": null,
          "roles": [
            "PerformerOf"
          ],
          "predicted_score": 2.453465
        },
        {
          "person_id": 7150,
          "name": "Qiang Luo",
          "stage_name": null,
          "roles": [
            "PerformerOf",
            "ProducerOf"
          ],
          "predicted_score": 2.3794196
        },
        {
          "person_id": 7151,
          "name": "Yong Ye",
          "stage_name": null,
          "roles": [
            "PerformerOf"
          ],
          "predicted_score": 2.3794196
        },
        {
          "person_id": 7149,
          "name": "Li Huang",
          "stage_name": null,
          "roles": [
            "PerformerOf"
          ],
          "predicted_score": 2.3793988
        }
      ]
    },
    {
      "id": "song:9446",
      "work_type": "Song",
      "work_id": 9446,
      "title": "Classical Fragments",
      "genre": "Desert Rock",
      "notable": true,
      "release_year": 2027,
      "single": true,
      "own": false,
      "artist_id": 9447,
      "artist_name": "Jie Fang",
      "influence": 0,
      "influence_breakdown": {
        "cover": 0,
        "sample": 0,
        "reference": 0,
        "style": 0
      },
      "relation_types": [
        "DirectlySamples"
      ],
      "collaborators": [
        {
          "person_id": 1785,
          "name": "Ping Zeng",
          "stage_name": null,
          "roles": [
            "LyricistOf"
          ],
          "predicted_score": 4.475672
        },
        {
          "person_id": 9447,
          "name": "Jie Fang",
          "stage_name": null,
          "roles": [
            "PerformerOf",
            "ProducerOf"
          ],
          "predicted_score": 2.3985531
        },
        {
          "person_id": 9448,
          "name": "Yan Qin",
          "stage_name": null,
          "roles": [
            "PerformerOf"
          ],
          "predicted_score": 2.3985531
        }
      ]
    },
    {
      "id": "song:11706",
      "work_type": "Song",
      "work_id": 11706,
      "title": "Quantum Woodwind",
      "genre": "Space Rock",
      "notable": false,
      "release_year": 2029,
      "single": true,
      "own": false,
      "artist_id": 11707,
      "artist_name": "Lei Ma",
      "influence": 0,
      "influence_breakdown": {
        "cover": 0,
        "sample": 0,
        "reference": 0,
        "style": 0
      },
      "relation_types": [
        "CoverOf"
      ],
      "collaborators": [
        {
          "person_id": 11707,
          "name": "Lei Ma",
          "stage_name": null,
          "roles": [
            "PerformerOf"
          ],
          "predicted_score": 2.397953
        },
        {
          "person_id": 11708,
          "name": "Yan Cheng",
          "stage_name": null,
          "roles": [
            "PerformerOf"
          ],
          "predicted_score": 2.397953
        },
        {
          "person_id": 11709,
          "name": "Gang Wen",
          "stage_name": null,
          "roles": [
            "PerformerOf"
          ],
          "predicted_score": 2.397953
        },
        {
          "person_id": 11710,
          "name": "Jie Hao",
          "stage_name": null,
          "roles": [
            "PerformerOf"
          ],
          "predicted_score": 2.397953
        },
        {
          "person_id": 11711,
          "name": "Shota Suzuki",
          "stage_name": null,
          "roles": [
            "PerformerOf"
          ],
          "predicted_score": 2.397953
        }
      ]
    },
    {
      "id": "song:5088",
      "work_type": "Song",
      "work_id": 5088,
      "title": "Echoes of a Lonely Gaze",
      "genre": "Lo-Fi Electronica",
      "notable": true,
      "release_year": 2026,
      "single": false,
      "own": false,
      "artist_id": 7,
      "artist_name": "Xiulan Zeng",
      "influence": 0,
      "influence_breakdown": {
        "cover": 0,
        "sample": 0,
        "reference": 0,
        "style": 0
      },
      "relation_types": [
        "LyricalReferenceTo"
      ],
      "collaborators": [
        {
          "person_id": 7,
          "name": "Xiulan Zeng",
          "stage_name": null,
          "roles": [
            "PerformerOf"
          ],
          "predicted_score": 4.2590513
        }
      ]
    },
    {
      "id": "song:7054",
      "work_type": "Song",
      "work_id": 7054,
      "title": "Whispers of the Caravan",
      "genre": "Lo-Fi Electronica",
      "notable": false,
      "release_year": 2026,
      "single": true,
      "own": false,
      "artist_id": 7,
      "artist_name": "Xiulan Zeng",
      "influence": 0,
      "influence_breakdown": {
        "cover": 0,
        "sample": 0,
        "reference": 0,
        "style": 0
      },
      "relation_types": [
        "InStyleOf"
      ],
      "collaborators": [
        {
          "person_id": 7,
          "name": "Xiulan Zeng",
          "stage_name": null,
          "roles": [
            "PerformerOf"
          ],
          "predicted_score": 4.2590513
        },
        {
          "person_id": 7055,
          "name": "Lei Duan",
          "stage_name": null,
          "roles": [
            "PerformerOf"
          ],
          "predicted_score": 3.786564
        },
        {
          "person_id": 8,
          "name": "David Franklin",
          "stage_name": null,
          "roles": [
            "PerformerOf"
          ],
          "predicted_score": 3.0771239
        }
      ]
    },
    {
      "id": "album:13567",
      "work_type": "Album",
      "work_id": 13567,
      "title": "Lowered Expectations",
      "genre": "Lo-Fi Electronica",
      "notable": true,
      "release_year": 2025,
      "single": false,
      "own": false,
      "artist_id": 7,
      "artist_name": "Xiulan Zeng",
      "influence": 0,
      "influence_breakdown": {
        "cover": 0,
        "sample": 0,
        "reference": 0,
        "style": 0
      },
      "relation_types": [
        "CoverOf"
      ],
      "collaborators": [
        {
          "person_id": 7,
          "name": "Xiulan Zeng",
          "stage_name": null,
          "roles": [
            "PerformerOf",
            "ProducerOf"
          ],
          "predicted_score": 4.2590513
        },
        {
          "person_id": 8,
          "name": "David Franklin",
          "stage_name": null,
          "roles": [
            "LyricistOf"
          ],
          "predicted_score": 3.0771239
        }
      ]
    },
    {
      "id": "song:14175",
      "work_type": "Song",
      "work_id": 14175,
      "title": "Our Unwritten Story",
      "genre": "Emo/Pop Punk",
      "notable": true,
      "release_year": 2031,
      "single": true,
      "own": false,
      "artist_id": 14176,
      "artist_name": "Fang Ren",
      "influence": 0,
      "influence_breakdown": {
        "cover": 0,
        "sample": 0,
        "reference": 0,
        "style": 0
      },
      "relation_types": [
        "InStyleOf"
      ],
      "collaborators": [
        {
          "person_id": 7,
          "name": "Xiulan Zeng",
          "stage_name": null,
          "roles": [
            "ProducerOf"
          ],
          "predicted_score": 4.2590513
        },
        {
          "person_id": 14176,
          "name": "Fang Ren",
          "stage_name": null,
          "roles": [
            "ComposerOf",
            "PerformerOf"
          ],
          "predicted_score": 2.3959937
        }
      ]
    }
  ],
  "links": [
    {
      "source": "song:14279",
      "target": "song:11467",
      "type": "LyricalReferenceTo"
    },
    {
      "source": "song:7054",
      "target": "song:11467",
      "type": "InStyleOf"
    },
    {
      "source": "album:13567",
      "target": "song:11467",
      "type": "CoverOf"
    },
    {
      "source": "song:7089",
      "target": "song:6054",
      "type": "InStyleOf"
    },
    {
      "source": "song:5088",
      "target": "song:11467",
      "type": "LyricalReferenceTo"
    },
    {
      "source": "song:9446",
      "target": "song:13516",
      "type": "DirectlySamples"
    },
    {
      "source": "song:13158",
      "target": "song:6054",
      "type": "InterpolatesFrom"
    },
    {
      "source": "album:7147",
      "target": "song:13516",
      "type": "InStyleOf"
    },
    {
      "source": "song:14175",
      "target": "song:11467",
      "type": "InStyleOf"
    },
    {
      "source": "song:11706",
      "target": "song:15222",
      "type": "CoverOf"
    }
  ]
}