{
  "person_id": 15575,
  "name": "Tao Mo",
  "stage_name": "Halogen Visions",
  "nodes": [
    {
      "id": "song:15574",
      "song_id": 15574,
      "title": "Shadows of a Forbidden Embrace",
      "genre": "Indie Folk",
      "notable": true,
      "release_year": 2013,
      "single": true,
      "own": true,
      "artist_id": 15575,
      "artist_name": "Tao Mo (Halogen Visions)",
      "influence": 2,
      "influence_breakdown": {
        "cover": 0,
        "sample": 0,
        "reference": 0,
        "style": 1
      },
      "relation_types": []
    },
    {
      "id": "song:6218",
      "song_id": 6218,
      "title": "Echoes of Grace in Silent Moments",
      "genre": "Doom Metal",
      "notable": true,
      "release_year": 2023,
      "single": true,
      "own": false,
      "artist_id": 6219,
      "artist_name": "Fang Yao",
      "influence": 0,
      "influence_breakdown": {
        "cover": 0,
        "sample": 0,
        "reference": 0,
        "style": 0
      },
      "relation_types": [
        "InStyleOf"
      ]
    }
  ],
  "links": [
    {
      "source": "song:6218",
      "target": "song:15574",
      "type": "InStyleOf"
    }
  ]
}