{
  "person_id": 2409,
  "name": "Chad Gibson",
  "stage_name": null,
  "nodes": [
    {
      "id": "song:2406",
      "work_type": "Song",
      "work_id": 2406,
      "title": "The Sovereign's Heart",
      "genre": "Symphonic Metal",
      "notable": true,
      "release_year": 2029,
      "single": false,
      "own": true,
      "artist_id": 2409,
      "artist_name": "Chad Gibson",
      "influence": 0,
      "influence_breakdown": {
        "cover": 0,
        "sample": 0,
        "reference": 0,
        "style": 0
      },
      "relation_types": [],
      "collaborators": [
        {
          "person_id": 1410,
          "name": "Guiying Yan",
          "stage_name": null,
          "roles": [
            "PerformerOf",
            "ProducerOf"
          ],
          "predicted_score": 4.384091
        },
        {
          "person_id": 579,
          "name": "Lei Fu",
          "stage_name": null,
          "roles": [
            "ProducerOf"
          ],
          "predicted_score": 3.4243224
        },
        {
          "person_id": 2407,
          "name": "Yuki Saito",
          "stage_name": " Vale",
          "roles": [
            "ComposerOf",
            "PerformerOf"
          ],
          "predicted_score": 2.9851894
        },
        {
          "person_id": 2408,
          "name": "Pamela Mitchell",
          "stage_name": null,
          "roles": [
            "PerformerOf"
          ],
          "predicted_score": 2.3953576
        }
      ]
    }
  ],
  "links": []
}