{
  "person_id": 3161,
  "name": "Min Zhao",
  "stage_name": null,
  "nodes": [
    {
      "id": "song:3160",
      "work_type": "Song",
      "work_id": 3160,
      "title": "Tied Together by Gravity",
      "genre": "Symphonic Metal",
      "notable": true,
      "release_year": 2017,
      "single": true,
      "own": true,
      "artist_id": 3161,
      "artist_name": "Min Zhao",
      "influence": 5,
      "influence_breakdown": {
        "cover": 0,
        "sample": 0,
        "reference": 1,
        "style": 1
      },
      "relation_types": [],
      "collaborators": [
        {
          "person_id": 2023,
          "name": "Qiang Tang",
          "stage_name": null,
          "roles": [
            "LyricistOf",
            "PerformerOf"
          ],
          "predicted_score": 5.197894
        },
        {
          "person_id": 3162,
          "name": "Xiuying Cai",
          "stage_name": null,
          "roles": [
            "ComposerOf"
          ],
          "predicted_score": 3.067086
        }
      ]
    },
    {
      "id": "album:2873",
      "work_type": "Album",
      "work_id": 2873,
      "title": "Symphonic Snowfall",
      "genre": "Symphonic Metal",
      "notable": true,
      "release_year": 2023,
      "single": false,
      "own": false,
      "artist_id": 2546,
      "artist_name": "Erdogan Baum",
      "influence": 0,
      "influence_breakdown": {
        "cover": 0,
        "sample": 0,
        "reference": 0,
        "style": 0
      },
      "relation_types": [
        "LyricalReferenceTo"
      ],
      "collaborators": [
        {
          "person_id": 779,
          "name": "Yang Zhao",
          "stage_name": null,
          "roles": [
            "ComposerOf"
          ],
          "predicted_score": 4.3984494
        },
        {
          "person_id": 2877,
          "name": "Juan Zhong",
          "stage_name": null,
          "roles": [
            "PerformerOf"
          ],
          "predicted_score": 4.108218
        },
        {
          "person_id": 2546,
          "name": "Erdogan Baum",
          "stage_name": null,
          "roles": [
            "LyricistOf",
            "PerformerOf"
          ],
          "predicted_score": 3.9297671
        },
        {
          "person_id": 2878,
          "name": "Anaïs Wagner",
          "stage_name": null,
          "roles": [
            "ProducerOf"
          ],
          "predicted_score": 3.4267962
        },
        {
          "person_id": 2588,
          "name": "Jun Mao",
          "stage_name": null,
          "roles": [
            "ComposerOf"
          ],
          "predicted_score": 3.0526838
        },
        {
          "person_id": 2874,
          "name": "Yang Kong",
          "stage_name": null,
          "roles": [
            "PerformerOf"
          ],
          "predicted_score": 2.4006898
        },
        {
          "person_id": 2875,
          "name": "Ping Luo",
          "stage_name": null,
          "roles": [
            "PerformerOf"
          ],
          "predicted_score": 2.4006898
        },
        {
          "person_id": 2876,
          "name": "Min Cai",
          "stage_name": null,
          "roles": [
            "PerformerOf"
          ],
          "predicted_score": 2.4006898
        }
      ]
    },
    {
      "id": "song:14167",
      "work_type": "Song",
      "work_id": 14167,
      "title": "Rhythms Between Our Doorsteps",
      "genre": "Indie Folk",
      "notable": true,
      "release_year": 2026,
      "single": true,
      "own": false,
      "artist_id": 5772,
      "artist_name": "Min Qian",
      "influence": 0,
      "influence_breakdown": {
        "cover": 0,
        "sample": 0,
        "reference": 0,
        "style": 0
      },
      "relation_types": [
        "InStyleOf"
      ],
      "collaborators": [
        {
          "person_id": 5772,
          "name": "Min Qian",
          "stage_name": null,
          "roles": [
            "PerformerOf",
            "ProducerOf"
          ],
          "predicted_score": 3.7147346
        },
        {
          "person_id": 11346,
          "name": "Jie Zhong",
          "stage_name": null,
          "roles": [
            "PerformerOf"
          ],
          "predicted_score": 3.4290311
        },
        {
          "person_id": 11343,
          "name": "Min Yao",
          "stage_name": null,
          "roles": [
            "PerformerOf"
          ],
          "predicted_score": 3.042127
        },
        {
          "person_id": 14168,
          "name": "Juan Tan",
          "stage_name": null,
          "roles": [
            "ComposerOf"
          ],
          "predicted_score": 2.3979325
        }
      ]
    }
  ],
  "links": [
    {
      "source": "song:14167",
      "target": "song:3160",
      "type": "InStyleOf"
    },
    {
      "source": "album:2873",
      "target": "song:3160",
      "type": "LyricalReferenceTo"
    }
  ]
}