{
  "person_id": 5149,
  "name": "Lei Jiang",
  "stage_name": null,
  "nodes": [
    {
      "id": "song:5146",
      "song_id": 5146,
      "title": "Waste Management Waltz",
      "genre": "Darkwave",
      "notable": true,
      "release_year": 2026,
      "single": false,
      "own": true,
      "artist_id": 5149,
      "artist_name": "Lei Jiang",
      "influence": 2,
      "influence_breakdown": {
        "cover": 0,
        "sample": 0,
        "reference": 0,
        "style": 1
      },
      "relation_types": []
    },
    {
      "id": "song:16354",
      "song_id": 16354,
      "title": "Farmland Titans",
      "genre": "Darkwave",
      "notable": true,
      "release_year": 2027,
      "single": true,
      "own": false,
      "artist_id": 5151,
      "artist_name": "Linda Santos",
      "influence": 0,
      "influence_breakdown": {
        "cover": 0,
        "sample": 0,
        "reference": 0,
        "style": 0
      },
      "relation_types": [
        "InStyleOf"
      ]
    }
  ],
  "links": [
    {
      "source": "song:16354",
      "target": "song:5146",
      "type": "InStyleOf"
    }
  ]
}