{
  "person_id": 9380,
  "name": "Jun Dai",
  "stage_name": null,
  "nodes": [
    {
      "id": "song:12793",
      "song_id": 12793,
      "title": "Abandoned Melodies",
      "genre": "Avant-Garde Folk",
      "notable": true,
      "release_year": 2004,
      "single": false,
      "own": true,
      "artist_id": 9380,
      "artist_name": "Jun Dai",
      "influence": 13,
      "influence_breakdown": {
        "cover": 0,
        "sample": 0,
        "reference": 3,
        "style": 2
      },
      "relation_types": []
    },
    {
      "id": "song:9378",
      "song_id": 9378,
      "title": "The Space Between Landmarks",
      "genre": "Psychedelic Rock",
      "notable": true,
      "release_year": 2024,
      "single": false,
      "own": true,
      "artist_id": 9380,
      "artist_name": "Jun Dai",
      "influence": 2,
      "influence_breakdown": {
        "cover": 0,
        "sample": 0,
        "reference": 0,
        "style": 1
      },
      "relation_types": []
    },
    {
      "id": "song:12617",
      "song_id": 12617,
      "title": "Forbidden Terrain",
      "genre": "Americana",
      "notable": true,
      "release_year": 2020,
      "single": false,
      "own": true,
      "artist_id": 9380,
      "artist_name": "Jun Dai",
      "influence": 6,
      "influence_breakdown": {
        "cover": 0,
        "sample": 0,
        "reference": 2,
        "style": 0
      },
      "relation_types": []
    },
    {
      "id": "song:13282",
      "song_id": 13282,
      "title": "Greenback Swagger",
      "genre": "Jazz Surf Rock",
      "notable": true,
      "release_year": 2027,
      "single": true,
      "own": true,
      "artist_id": 9380,
      "artist_name": "Jun Dai",
      "influence": 2,
      "influence_breakdown": {
        "cover": 0,
        "sample": 0,
        "reference": 0,
        "style": 1
      },
      "relation_types": []
    },
    {
      "id": "song:14146",
      "song_id": 14146,
      "title": "Armor of Passion",
      "genre": "Jazz Surf Rock",
      "notable": true,
      "release_year": 2028,
      "single": false,
      "own": true,
      "artist_id": 9380,
      "artist_name": "Jun Dai",
      "influence": 0,
      "influence_breakdown": {
        "cover": 0,
        "sample": 0,
        "reference": 0,
        "style": 0
      },
      "relation_types": []
    },
    {
      "id": "song:695",
      "song_id": 695,
      "title": "Roots and Rhythms",
      "genre": "Avant-Garde Folk",
      "notable": true,
      "release_year": 2012,
      "single": true,
      "own": false,
      "artist_id": 697,
      "artist_name": "Yong Zheng",
      "influence": 0,
      "influence_breakdown": {
        "cover": 0,
        "sample": 0,
        "reference": 0,
        "style": 0
      },
      "relation_types": [
        "LyricalReferenceTo"
      ]
    },
    {
      "id": "song:9104",
      "song_id": 9104,
      "title": "Echoes of Sunrise",
      "genre": "Indie Pop",
      "notable": true,
      "release_year": 2014,
      "single": true,
      "own": false,
      "artist_id": 2537,
      "artist_name": "Gang Mo",
      "influence": 0,
      "influence_breakdown": {
        "cover": 0,
        "sample": 0,
        "reference": 0,
        "style": 0
      },
      "relation_types": [
        "InStyleOf"
      ]
    },
    {
      "id": "song:11244",
      "song_id": 11244,
      "title": "Echoes of a Vanishing Embrace",
      "genre": "Alternative Rock",
      "notable": true,
      "release_year": 2007,
      "single": true,
      "own": false,
      "artist_id": 697,
      "artist_name": "Yong Zheng",
      "influence": 0,
      "influence_breakdown": {
        "cover": 0,
        "sample": 0,
        "reference": 0,
        "style": 0
      },
      "relation_types": [
        "InterpolatesFrom"
      ]
    },
    {
      "id": "song:11299",
      "song_id": 11299,
      "title": "Backwards in the Saddle",
      "genre": "Avant-Garde Folk",
      "notable": true,
      "release_year": 2009,
      "single": true,
      "own": false,
      "artist_id": 697,
      "artist_name": "Yong Zheng",
      "influence": 0,
      "influence_breakdown": {
        "cover": 0,
        "sample": 0,
        "reference": 0,
        "style": 0
      },
      "relation_types": [
        "InStyleOf"
      ]
    },
    {
      "id": "song:11514",
      "song_id": 11514,
      "title": "Selfie Syndrome",
      "genre": "Emo/Pop Punk",
      "notable": true,
      "release_year": 2007,
      "single": true,
      "own": false,
      "artist_id": 882,
      "artist_name": "Yan Jin",
      "influence": 0,
      "influence_breakdown": {
        "cover": 0,
        "sample": 0,
        "reference": 0,
        "style": 0
      },
      "relation_types": [
        "InterpolatesFrom"
      ]
    },
    {
      "id": "song:1797",
      "song_id": 1797,
      "title": "Scandinavian Dreams",
      "genre": "Americana",
      "notable": true,
      "release_year": 2028,
      "single": true,
      "own": false,
      "artist_id": 1798,
      "artist_name": "Ping Xia",
      "influence": 0,
      "influence_breakdown": {
        "cover": 0,
        "sample": 0,
        "reference": 0,
        "style": 0
      },
      "relation_types": [
        "InStyleOf"
      ]
    },
    {
      "id": "song:6137",
      "song_id": 6137,
      "title": "Beyond the Moment",
      "genre": "Synthwave",
      "notable": true,
      "release_year": 2024,
      "single": true,
      "own": false,
      "artist_id": 6139,
      "artist_name": "Russell Barnes",
      "influence": 0,
      "influence_breakdown": {
        "cover": 0,
        "sample": 0,
        "reference": 0,
        "style": 0
      },
      "relation_types": [
        "InterpolatesFrom"
      ]
    },
    {
      "id": "song:14047",
      "song_id": 14047,
      "title": "Montmartre Petals",
      "genre": "Space Rock",
      "notable": true,
      "release_year": 2022,
      "single": true,
      "own": false,
      "artist_id": 4753,
      "artist_name": "Bartek Krężołek ( Neon Ghost)",
      "influence": 0,
      "influence_breakdown": {
        "cover": 0,
        "sample": 0,
        "reference": 0,
        "style": 0
      },
      "relation_types": [
        "InterpolatesFrom"
      ]
    },
    {
      "id": "song:15981",
      "song_id": 15981,
      "title": "Memories in the Rearview",
      "genre": "Jazz Surf Rock",
      "notable": true,
      "release_year": 2029,
      "single": true,
      "own": false,
      "artist_id": 15556,
      "artist_name": "Yong Liu",
      "influence": 0,
      "influence_breakdown": {
        "cover": 0,
        "sample": 0,
        "reference": 0,
        "style": 0
      },
      "relation_types": [
        "InStyleOf"
      ]
    }
  ],
  "links": [
    {
      "source": "song:1797",
      "target": "song:9378",
      "type": "InStyleOf"
    },
    {
      "source": "song:695",
      "target": "song:12793",
      "type": "LyricalReferenceTo"
    },
    {
      "source": "song:15981",
      "target": "song:13282",
      "type": "InStyleOf"
    },
    {
      "source": "song:14047",
      "target": "song:12617",
      "type": "InterpolatesFrom"
    },
    {
      "source": "song:11299",
      "target": "song:12793",
      "type": "InStyleOf"
    },
    {
      "source": "song:11244",
      "target": "song:12793",
      "type": "InterpolatesFrom"
    },
    {
      "source": "song:6137",
      "target": "song:12617",
      "type": "InterpolatesFrom"
    },
    {
      "source": "song:9104",
      "target": "song:12793",
      "type": "InStyleOf"
    },
    {
      "source": "song:11514",
      "target": "song:12793",
      "type": "InterpolatesFrom"
    }
  ]
}