{
  "person_id": 9527,
  "name": "Paul Lewis",
  "stage_name": null,
  "nodes": [
    {
      "id": "song:9526",
      "song_id": 9526,
      "title": "Prismatic Improvisations",
      "genre": "Synthwave",
      "notable": true,
      "release_year": 2001,
      "single": false,
      "own": true,
      "artist_id": 9527,
      "artist_name": "Paul Lewis",
      "influence": 13,
      "influence_breakdown": {
        "cover": 0,
        "sample": 1,
        "reference": 1,
        "style": 3
      },
      "relation_types": []
    },
    {
      "id": "song:14241",
      "song_id": 14241,
      "title": "Trenchcoat Memory",
      "genre": "Synthwave",
      "notable": true,
      "release_year": 1991,
      "single": true,
      "own": true,
      "artist_id": 9527,
      "artist_name": "Paul Lewis",
      "influence": 6,
      "influence_breakdown": {
        "cover": 0,
        "sample": 0,
        "reference": 2,
        "style": 0
      },
      "relation_types": []
    },
    {
      "id": "song:970",
      "song_id": 970,
      "title": "Wooden Heart",
      "genre": "Alternative Rock",
      "notable": true,
      "release_year": 2022,
      "single": true,
      "own": false,
      "artist_id": 972,
      "artist_name": "Robin Jones",
      "influence": 0,
      "influence_breakdown": {
        "cover": 0,
        "sample": 0,
        "reference": 0,
        "style": 0
      },
      "relation_types": [
        "LyricalReferenceTo"
      ]
    },
    {
      "id": "song:8409",
      "song_id": 8409,
      "title": "Circuit Forger",
      "genre": "Jazz Surf Rock",
      "notable": true,
      "release_year": 2029,
      "single": true,
      "own": false,
      "artist_id": 4255,
      "artist_name": "Guiying Zhou",
      "influence": 0,
      "influence_breakdown": {
        "cover": 0,
        "sample": 0,
        "reference": 0,
        "style": 0
      },
      "relation_types": [
        "InStyleOf"
      ]
    },
    {
      "id": "song:12190",
      "song_id": 12190,
      "title": "Sonic Whispers",
      "genre": "Indie Folk",
      "notable": true,
      "release_year": 2023,
      "single": false,
      "own": false,
      "artist_id": 12191,
      "artist_name": "Michael Baker",
      "influence": 0,
      "influence_breakdown": {
        "cover": 0,
        "sample": 0,
        "reference": 0,
        "style": 0
      },
      "relation_types": [
        "DirectlySamples"
      ]
    },
    {
      "id": "song:15007",
      "song_id": 15007,
      "title": "Cadenas de Deseo",
      "genre": "Synthwave",
      "notable": true,
      "release_year": 2003,
      "single": true,
      "own": false,
      "artist_id": 1002,
      "artist_name": "Li Wu",
      "influence": 0,
      "influence_breakdown": {
        "cover": 0,
        "sample": 0,
        "reference": 0,
        "style": 0
      },
      "relation_types": [
        "InStyleOf"
      ]
    },
    {
      "id": "song:16501",
      "song_id": 16501,
      "title": "Desperate Dash at the World's Boundary",
      "genre": "Synthwave",
      "notable": true,
      "release_year": 2000,
      "single": true,
      "own": false,
      "artist_id": 16502,
      "artist_name": "Guiying Kong (Blue Ashes)",
      "influence": 0,
      "influence_breakdown": {
        "cover": 0,
        "sample": 0,
        "reference": 0,
        "style": 0
      },
      "relation_types": [
        "InStyleOf"
      ]
    },
    {
      "id": "song:6398",
      "song_id": 6398,
      "title": "Sacred Brevity in Nine Movements",
      "genre": "Dream Pop",
      "notable": true,
      "release_year": 2008,
      "single": false,
      "own": false,
      "artist_id": 6399,
      "artist_name": "Jie Su",
      "influence": 0,
      "influence_breakdown": {
        "cover": 0,
        "sample": 0,
        "reference": 0,
        "style": 0
      },
      "relation_types": [
        "LyricalReferenceTo"
      ]
    },
    {
      "id": "song:16736",
      "song_id": 16736,
      "title": "Linguistic Limbo",
      "genre": "Dream Pop",
      "notable": true,
      "release_year": 2006,
      "single": true,
      "own": false,
      "artist_id": 6400,
      "artist_name": "Jason Warner",
      "influence": 0,
      "influence_breakdown": {
        "cover": 0,
        "sample": 0,
        "reference": 0,
        "style": 0
      },
      "relation_types": [
        "LyricalReferenceTo"
      ]
    }
  ],
  "links": [
    {
      "source": "song:15007",
      "target": "song:9526",
      "type": "InStyleOf"
    },
    {
      "source": "song:16501",
      "target": "song:9526",
      "type": "InStyleOf"
    },
    {
      "source": "song:6398",
      "target": "song:14241",
      "type": "LyricalReferenceTo"
    },
    {
      "source": "song:12190",
      "target": "song:9526",
      "type": "DirectlySamples"
    },
    {
      "source": "song:16736",
      "target": "song:14241",
      "type": "LyricalReferenceTo"
    },
    {
      "source": "song:8409",
      "target": "song:9526",
      "type": "InStyleOf"
    },
    {
      "source": "song:970",
      "target": "song:9526",
      "type": "LyricalReferenceTo"
    }
  ]
}